[
  {
    "stage_id": 1,
    "dates": "2月8日 至 2月11日",
    "location": "Christchurch",
    "itinerary": [
      {
        "date": "2/8",
        "activities": [
          "五點前往超市「PAK'nSAVE」採買"
        ]
      },
      {
        "date": "2/9",
        "activities": [
          "探索基督城市區 ＠zhi"
        ]
      },
      {
        "date": "2/10",
        "activities": [
          "Lyttelton 沿海小鎮 @Jane"
        ]
      },
      {
        "date": "2/11",
        "activities": [
          "Akaroa 法國小鎮 or 沿海步道 Taylor's Mistake  @Jane"
        ]
      }
    ]
  },
  {
    "stage_id": 2,
    "dates": "2月12日至2月14日",
    "location": "皇后鎮、Glenorchy",
    "itinerary": [
      {
        "date": "2/12",
        "activities": [
          "注意:從基督城出發至皇后鎮，車程6小時（500公里）早上10點出發，晚上7點左右到達 ",
          "(x)Rakaia River waterfall -> (x)The Rabbit (Ashburton) -> Geraldine Fairlie lookout",
          "Fairlie 有一間排隊的派店，六點開門 人潮多可能會超過20～30分鐘",
          "Burkes pass -> Dog Kennel Corner -> Lake Tekopo -> Lake Pukaki",
          "Omarama 買杯咖啡和汽油",
          "Lindis Scenic hill spot/Lindis pass viewpoint",
          "Cromwell-水果鎮 瓊斯太太的水果攤(Jones Family Fruit Stall),The Stoaker Room (Cromwell)",
          "皇后鎮外大超市採買"
        ]
      },
      {
        "date": "2/13",
        "activities": [
          "從皇后鎮前往Glenorchy，車程1小時（50公里）",
          "Routeburn Track 健行",
          "Glenorchy 落日？"
        ]
      },
      {
        "date": "2/14",
        "activities": [
          "農夫市場",
          "皇后鎮觀賞日落"
        ]
      }
    ]
  },
  {
    "stage_id": 3,
    "dates": "2月15日至2月19日",
    "location": "Te Anau",
    "itinerary": [
      {
        "date": "2/15",
        "activities": [
          "Fergburger排隊漢堡店七點開門",
          "注意: 從皇后鎮前往Te Anau，車程2小時（170公里）",
          "Jack’s Point Loop   這條2.5小時的環路大部分都是上坡，但山頂的景色美不勝收",
          "Mossburn/Kingston 加油便宜"
        ]
      },
      {
        "date": "2/16",
        "activities": [
          "探索 Mildford Sound/ Te Anau"
        ]
      },
      {
        "date": "2/17",
        "activities": [
          "探索 Mildford Sound/ Te Anau"
        ]
      },
      {
        "date": "2/18",
        "activities": [
          "探索 Mildford Sound/ Te Anau"
        ]
      },
      {
        "date": "2/19",
        "activities": [
          "探索 Mildford Sound/ Te Anau"
        ]
      }
    ]
  },
  {
    "stage_id": 4,
    "dates": "2月20日至2月24日",
    "location": "Wanaka",
    "itinerary": [
      {
        "date": "2/20",
        "activities": [
          "注意: Te Anau 前往 瓦納卡，車程3小時（230公里）",
          "Mossburn/Kingston 加油便宜?",
          "皇后鎮「PAK'nSAVE」超市採買",
          "Lake Hayes/ Arrowtown",
          "Arrow Junction lookout point",
          "Cardrona 餐廳—百年酒店The Cardrona Hotel  最有名的是羊肉漢堡，更推鹿肉（venison"
        ]
      },
      {
        "date": "2/21",
        "activities": [
          "自由活動或探索瓦納卡"
        ]
      },
      {
        "date": "2/22",
        "activities": [
          "自由活動或探索瓦納卡"
        ]
      },
      {
        "date": "2/23",
        "activities": [
          "自由活動或探索瓦納卡"
        ]
      },
      {
        "date": "2/24",
        "activities": [
          "自由活動或探索瓦納卡"
        ]
      }
    ]
  },
  {
    "stage_id": 5,
    "dates": "2月25日至2月26日",
    "location": "Twizel/Mt Cook",
    "itinerary": [
      {
        "date": "2/25",
        "activities": [
          "注意: 從瓦納卡前往Mt Cook，車程2.5小時（200公里）",
          "Kawasaki Gorge Suspension bridge",
          "Cromwell-水果鎮 採櫻桃  @chingwen",
          "Lindis Scenic hill spot/Lindis pass viewpoint",
          "Twizel High country salmon"
        ]
      },
      {
        "date": "2/26",
        "activities": [
          "於Mt Cook停留一整天，進行健行活動 @Jane"
        ]
      }
    ]
  },
  {
    "stage_id": 6,
    "dates": "2月27日至2月28日",
    "location": "Springfield 近基督城",
    "itinerary": [
      {
        "date": "2/27",
        "activities": [
          "注意: Twizel → Springfield：5小時，400公里",
          "Burkes pass  富含古蹟的街道", 
          "Rakaia Gorge Walkway 二月顏色沒春天漂亮，待確認值不值得去，離73公路近 @chingwen"
        ]
      },
      {
        "date": "2/28",
        "activities": [
          "於73號公路（Arthur's Pass）健行一日，車程1小時60公里. @Zhi"
        ]
      }
    ]
  },
  {
    "stage_id": 7,
    "dates": "3月1日至3月2日",
    "location": "基督城機場",
    "itinerary": [
      {
        "date": "3/1",
        "activities": [
          "從Springfield返回基督城，車程1小時60公里",
          "基督城- The Tannery 很有設計感的 mall",
          "注意:需於當日下午四點前完成還車",
          "超市購買紀念品與晚餐"
        ]
      },
      {
        "date": "3/2",
        "activities": [
          "注意:基督城機場回台航班：早上06:00起飛"
        ]
      }
    ]
  }
]